audiodata/__init__.py
audiodata/metadata.py
audiodata-1.1.1.dist-info/LICENSE
audiodata-1.1.1.dist-info/METADATA
audiodata-1.1.1.dist-info/WHEEL
audiodata-1.1.1.dist-info/top_level.txt
audiodata-1.1.1.dist-info/RECORD
