Metadata-Version: 2.1
Name: audiodata
Version: 1.1.1
Summary: Get accurate audio metadata from any audio file. Supports MP3, FLAC, WAV, OGG and more.
Author-email: Shreyan Basu Ray <shreyan.github@gmail.com>
License: Copyright (c) 2012-2024 Scott Chacon and others
Project-URL: Issues, https://github.com/Shreyan1/WhisperMe-Audio-Transcriber/issues
Keywords: audio,metadata,audiodata,data,secret
Classifier: Programming Language :: Python :: 3
Classifier: License :: OSI Approved :: MIT License
Classifier: Operating System :: OS Independent
Requires-Python: >=3.10
License-File: LICENSE
Requires-Dist: pydub
Requires-Dist: mutagen
